phylokrr/__init__.py
phylokrr/core.py
phylokrr/datasets.py
phylokrr/inspection.py
phylokrr/kernels.py
phylokrr/metrics.py
phylokrr/phylosig.py
phylokrr/utils.py
phylokrr/data/test_cov.csv
phylokrr/data/test_cov2.csv
phylokrr/data/test_data.csv
phylokrr/data/test_data2.csv
phylokrr/data/test_data_unweigthed.csv
phylokrr/data/test_log_data.csv
phylokrr-0.5.0.dist-info/METADATA
phylokrr-0.5.0.dist-info/WHEEL
phylokrr-0.5.0.dist-info/top_level.txt
phylokrr-0.5.0.dist-info/RECORD
