Metadata-Version: 2.1
Name: phylokrr
Version: 0.5.0
Summary: UNKNOWN
Home-page: UNKNOWN
License: UNKNOWN
Platform: UNKNOWN
Classifier: Programming Language :: Python :: 3
Requires-Python: >=3.5
Requires-Dist: numpy
